cloudflare_peek/__init__.py
cloudflare_peek/cli.py
cloudflare_peek/core/__init__.py
cloudflare_peek/core/detector.py
cloudflare_peek/core/scraper.py
cloudflare_peek/examples/__init__.py
cloudflare_peek/examples/basic_example.py
cloudflare_peek/examples/event_loop_test.py
cloudflare_peek/utils/__init__.py
cloudflare_peek-0.1.0.dist-info/licenses/LICENSE
cloudflare_peek-0.1.0.dist-info/METADATA
cloudflare_peek-0.1.0.dist-info/WHEEL
cloudflare_peek-0.1.0.dist-info/entry_points.txt
cloudflare_peek-0.1.0.dist-info/top_level.txt
cloudflare_peek-0.1.0.dist-info/RECORD
