Metadata-Version: 2.4
Name: cloudflare-peek
Version: 0.1.0
Summary: A Python utility for scraping Cloudflare-protected websites using screenshot + OCR fallback
Author-email: Talha Ali <your-email@example.com>
Maintainer-email: Talha Ali <your-email@example.com>
License: MIT
Project-URL: Homepage, https://github.com/Talha-Ali-5365/CloudflarePeek
Project-URL: Repository, https://github.com/Talha-Ali-5365/CloudflarePeek
Project-URL: Documentation, https://github.com/Talha-Ali-5365/CloudflarePeek#readme
Project-URL: Bug Tracker, https://github.com/Talha-Ali-5365/CloudflarePeek/issues
Keywords: scraping,cloudflare,ocr,screenshot,web-scraping,bypass
Classifier: Development Status :: 4 - Beta
Classifier: Intended Audience :: Developers
Classifier: License :: OSI Approved :: MIT License
Classifier: Operating System :: OS Independent
Classifier: Programming Language :: Python :: 3
Classifier: Programming Language :: Python :: 3.8
Classifier: Programming Language :: Python :: 3.9
Classifier: Programming Language :: Python :: 3.10
Classifier: Programming Language :: Python :: 3.11
Classifier: Programming Language :: Python :: 3.12
Classifier: Topic :: Internet :: WWW/HTTP :: Browsers
Classifier: Topic :: Software Development :: Libraries :: Python Modules
Classifier: Topic :: Text Processing
Requires-Python: >=3.8
License-File: LICENSE
Requires-Dist: requests>=2.25.0
Requires-Dist: langchain-community>=0.0.20
Requires-Dist: playwright>=1.40.0
Requires-Dist: google-generativeai>=0.3.0
Requires-Dist: Pillow>=8.0.0
Requires-Dist: typer[all]>=0.9.0
Requires-Dist: rich>=13.0.0
Provides-Extra: dev
Requires-Dist: pytest>=6.0; extra == "dev"
Requires-Dist: pytest-asyncio>=0.21.0; extra == "dev"
Requires-Dist: black>=22.0.0; extra == "dev"
Requires-Dist: flake8>=4.0.0; extra == "dev"
Requires-Dist: mypy>=0.991; extra == "dev"
Requires-Dist: twine>=4.0.0; extra == "dev"
Dynamic: license-file
